{"id": "cs001", "text": "Sort the following headlines into topic categories.", "items": ["NASA discovers high concentrations of water ice beneath the Martian surface", "Apple unveils a new augmented reality headset aimed at developers", "Clinical trial shows promising results for a universal flu vaccine", "Global streaming platform reports record subscriber growth this quarter", "Startup raises $50 million to develop autonomous delivery drones"]}
{"id": "cs002", "text": "Categorize these news items by topic.", "items": ["Researchers achieve quantum error correction at room temperature", "Major automaker announces transition to fully electric fleet by 2030", "New study links gut microbiome diversity to improved mental health outcomes", "Box office revenues for the summer season surpass pre-pandemic levels", "Central bank raises interest rates for the third consecutive quarter"]}
{"id": "cs003", "text": "Assign each headline to the most appropriate topic group.", "items": ["CRISPR gene therapy receives FDA approval for sickle cell disease treatment", "Social media company launches AI-powered content moderation system", "Astronomers detect a potentially habitable exoplanet within 40 light-years", "Multinational conglomerate completes largest merger in a decade", "Award-winning director announces trilogy adaptation of classic novel"]}
{"id": "cs004", "text": "Sort these items into the provided topic categories.", "items": ["Wearable biosensor can detect early signs of dehydration in athletes", "Open-source language model outperforms proprietary rivals on benchmarks", "Deep-sea expedition discovers three previously unknown species near hydrothermal vents", "Venture capital funding for climate tech startups doubles year over year", "Popular video game franchise announces live-action television adaptation"]}
{"id": "cs005", "text": "Place each headline into the best-matching topic group.", "items": ["Breakthrough in solid-state battery technology promises faster charging and longer range", "Pharmaceutical giant recalls high blood pressure medication due to contamination", "Physicists confirm new particle consistent with predictions from the Standard Model", "E-commerce platform reports highest single-day sales volume in its history", "Music streaming service introduces spatial audio for all subscribers"]}
